lowball_arangodb_authdb/__init__.py
lowball_arangodb_authdb/authdb.py
lowball_arangodb_authdb/token_validators.py
tests/__init__.py
tests/conftest.py
tests/test_authdb.py
tests/test_token_validators.py
lowball_arangodb_authdb-1.0.0.dist-info/LICENSE
lowball_arangodb_authdb-1.0.0.dist-info/METADATA
lowball_arangodb_authdb-1.0.0.dist-info/WHEEL
lowball_arangodb_authdb-1.0.0.dist-info/top_level.txt
lowball_arangodb_authdb-1.0.0.dist-info/RECORD
