Metadata-Version: 2.1
Name: lowball-arangodb-authdb
Version: 1.0.0
Summary: An Authentication Database for lowball that uses ArangoDB to store token information
Home-page: https://github.com/EmersonElectricCo/lowball-arangodb-authdb
Author: Isaiah Eichen
Author-email: ieichen137@gmail.com
License: Apache License 2.0
Platform: UNKNOWN
Requires-Dist: lowball
Requires-Dist: pyarango (>=1.3.5)
